biskit/__init__.py
biskit/amberResidueLibrary.py
biskit/amberResidues.py
biskit/atomCharger.py
biskit/biounit.py
biskit/colorspectrum.py
biskit/edparser.py
biskit/errorHandler.py
biskit/errors.py
biskit/gnuplot.py
biskit/hist.py
biskit/logFile.py
biskit/match2seq.py
biskit/mathUtils.py
biskit/matrixPlot.py
biskit/molUtils.py
biskit/pdbCleaner.py
biskit/pdbDope.py
biskit/pdbModel.py
biskit/plotUtils.py
biskit/profileCollection.py
biskit/ramachandran.py
biskit/reducecoordinates.py
biskit/rmsFit.py
biskit/settings.py
biskit/test.py
biskit/tools.py
biskit/wlc.py
biskit/xplorModel.py
biskit/core/__init__.py
biskit/core/bislist.py
biskit/core/dictlist.py
biskit/core/difflib_old.py
biskit/core/localpath.py
biskit/core/pdbparseFile.py
biskit/core/pdbparseModel.py
biskit/core/pdbparseNCBI.py
biskit/core/pdbparsePickle.py
biskit/core/pdbparser.py
biskit/core/pdbparserFactory.py
biskit/core/settingsManager.py
biskit/core/settingsParser.py
biskit/core/trajparseAmberCrd.py
biskit/core/trajparseNetCDF.py
biskit/core/trajparsePDBs.py
biskit/core/trajparser.py
biskit/core/trajparserFactory.py
biskit/core/oldnumeric/__analyze_oldnumeric.py
biskit/core/oldnumeric/__init__.py
biskit/core/oldnumeric/alter_code.py
biskit/core/oldnumeric/array_printer.py
biskit/core/oldnumeric/compat.py
biskit/core/oldnumeric/functions.py
biskit/core/oldnumeric/misc.py
biskit/core/oldnumeric/precision.py
biskit/core/oldnumeric/typeconv.py
biskit/core/oldnumeric/ufuncs.py
biskit/core/scientificIO/FortranFormat.py
biskit/core/scientificIO/PDB.py
biskit/core/scientificIO/PDBExportFilters.py
biskit/core/scientificIO/TextFile.py
biskit/core/scientificIO/__init__.py
biskit/data/spectrum.pl
biskit/data/amber/leap/ace_cap.pdb
biskit/data/amber/leap/nme_cap.pdb
biskit/data/amber/leap/solvate_box.leap
biskit/data/amber/residues/all_amino03.in
biskit/data/amber/residues/all_aminoct03.in
biskit/data/amber/residues/all_aminont03.in
biskit/data/amber/residues/all_nuc02.in
biskit/data/amber/residues/amino12.in
biskit-3.0.1.dist-info/LICENSE.txt
biskit-3.0.1.dist-info/METADATA
biskit-3.0.1.dist-info/WHEEL
biskit-3.0.1.dist-info/top_level.txt
biskit-3.0.1.dist-info/RECORD
